<?xml version="1.0" encoding="UTF-8"?>
<!--
  Copyright (C) 2010 Orbeon, Inc.

  This program is free software; you can redistribute it and/or modify it under the terms of the
  GNU Lesser General Public License as published by the Free Software Foundation; either version
  2.1 of the License, or (at your option) any later version.

  This program is distributed in the hope that it will be useful, but WITHOUT ANY WARRANTY;
  without even the implied warranty of MERCHANTABILITY or FITNESS FOR A PARTICULAR PURPOSE.
  See the GNU Lesser General Public License for more details.

  The full text of the license is available at http://www.gnu.org/copyleft/lesser.html
  -->
<xxforms:dialog xmlns:xhtml="http://www.w3.org/1999/xhtml"
      xmlns:xforms="http://www.w3.org/2002/xforms"
      xmlns:xs="http://www.w3.org/2001/XMLSchema"
      xmlns:ev="http://www.w3.org/2001/xml-events"
      xmlns:xi="http://www.w3.org/2001/XInclude"
      xmlns:xxi="http://orbeon.org/oxf/xml/xinclude"
      xmlns:xxforms="http://orbeon.org/oxf/xml/xforms"
      xmlns:fr="http://orbeon.org/oxf/xml/form-runner"
      xmlns:fb="http://orbeon.org/oxf/xml/form-builder"
      xmlns:saxon="http://saxon.sf.net/"

      id="fb-edit-help-dialog" appearance="full" model="fb-edit-help-model" level="modal">

    <xforms:label ref="$form-resources/dialog-help/dialog-title"/>

    <xhtml:div>
        <xforms:group class="fb-hide-alert">
            <xforms:textarea ref="help-text" id="fb-edit-help-dialog-text">
                <xforms:label ref="$form-resources/dialog-help/help-message/label"/>
            </xforms:textarea>
            <xhtml:div class="fr-dialog-buttons">
                <xforms:trigger class="fr-inplace-rename">
                    <xforms:label ref="$form-resources/apply/label"/>
                    <!-- Close and save upon DOMActivate -->
                    <xforms:dispatch ev:event="DOMActivate" name="xxforms-dialog-close" target="fb-edit-help-dialog">
                        <xxforms:context name="fb:save" select="true()"/>
                    </xforms:dispatch>
                </xforms:trigger>
                <xforms:output value="$form-resources/or/label"/>
                <xforms:trigger appearance="minimal" class="fr-inplace-cancel">
                    <xforms:label ref="$form-resources/cancel/label"/>
                    <!-- Close and cancel upon DOMActivate -->
                    <xforms:dispatch ev:event="DOMActivate" name="xxforms-dialog-close" target="fb-edit-help-dialog">
                        <xxforms:context name="fb:save" select="false()"/>
                    </xforms:dispatch>
                </xforms:trigger>
            </xhtml:div>
        </xforms:group>
    </xhtml:div>

    <!-- Save data upon close -->
    <!-- NOTE: We used to have not(event('fb:save') = false()), but we prefer explicit now because we may get
         an extra xxforms-dialog-close event sent by the client, in which case we don't want to do the processing -->
    <xforms:action ev:event="xxforms-dialog-close" if="event('fb:save')">
        <xxforms:variable name="instance" select="instance('fb-edit-help-instance')" as="element()"/>
        <xforms:setvalue ref="$form-instance/root()/saxon:evaluate($instance/result-path)" value="$instance/help-text"/>
    </xforms:action>

    <!-- Copy help value when the dialog opens -->
    <xforms:action ev:event="xxforms-dialog-open">
        <xxforms:variable name="instance" select="instance('fb-edit-help-instance')" as="element()"/>
        <xforms:setvalue ref="$instance/result-path" value="event('fb:node')/saxon:path()"/>
        <xforms:setvalue ref="$instance/help-text" value="event('fb:node')"/>
    </xforms:action>

    <xforms:model id="fb-edit-help-model">
        <xforms:instance id="fb-edit-help-instance">
            <instance>
                <help-text/>
                <result-path/>
            </instance>
        </xforms:instance>
    </xforms:model>
</xxforms:dialog>
