<!--
    Copyright (C) 2004 Orbeon, Inc.

    This program is free software; you can redistribute it and/or modify it under the terms of the
    GNU Lesser General Public License as published by the Free Software Foundation; either version
    2.1 of the License, or (at your option) any later version.

    This program is distributed in the hope that it will be useful, but WITHOUT ANY WARRANTY;
    without even the implied warranty of MERCHANTABILITY or FITNESS FOR A PARTICULAR PURPOSE.
    See the GNU Lesser General Public License for more details.

    The full text of the license is available at http://www.gnu.org/copyleft/lesser.html
-->
<config xmlns="http://www.orbeon.com/oxf/controller"
        xmlns:xu="http://www.xmldb.org/xupdate"
        xmlns:oxf="http://www.orbeon.com/oxf/processors">

    <!-- Files to serve directly -->
    <files path-info="*.gif"/>
    <files path-info="*.css"/>
    <files path-info="*.pdf"/>
    <files path-info="*.js"/>
    <files path-info="*.png"/>
    <files path-info="*.jpg"/>
    <files path-info="*.xsd"/>
    <files path-info="*.html" mime-type="text/html"/>
    <files path-info="*.java" mime-type="text/plain"/>
    <files path-info="*.txt" mime-type="text/plain"/>
    <files path-info="*.xq" mime-type="text/plain"/>

    <!-- Examples portal -->
    <page id="home" path-info="/" model="/examples-portal/page-flow.xpl"/>
    <page path-info="/goto-example/.+" matcher="oxf:perl5-matcher" model="/examples-portal/page-flow.xpl"/>
    <page path-info="/goto-source/.+" matcher="oxf:perl5-matcher" model="/examples-portal/page-flow.xpl"/>

    <!-- Dispatch resources for the examples. This is necessary, since portlets cannot serve resources directly by design. -->
    <page path-info="/direct/.*" matcher="oxf:perl5-matcher" model="/examples/dispatch.xpl"/>

    <!-- Struts Examples -->
    <page path-info="/examples-struts/.*" matcher="oxf:perl5-matcher" model="/examples-standalone/struts-view/model/struts.xpl"/>

    <!-- Examples that do not work within the examples portal -->
    <page path-info="/examples-standalone/.*" matcher="oxf:perl5-matcher" model="/examples/dispatch.xpl"/>

    <!-- Standalone Counter example -->
    <page path-info="/counter*" model="/examples/counter/page-flow.xpl"/>

    <!-- Standalone Forms example -->
    <page path-info="/forms*" model="/examples/forms/page-flow.xpl"/>

    <!-- Standalone BizDoc 2 example -->
    <page path-info="/bizdoc2*" model="/examples/bizdoc2/page-flow.xpl"/>

    <!-- Standalone Address Book 2 example -->
    <page path-info="/address-book2*" model="/examples/address-book2/page-flow.xpl"/>

    <!-- Standalone Blog example -->
    <page path-info="/blog*" model="/examples/blog/page-flow.xpl"/>

    <!-- Standalone Employees example -->
    <page path-info="/employees*" model="/examples/employees/page-flow.xpl"/>

    <!-- Standalone XForms Controls example -->
    <page path-info="/xforms-controls*" model="/examples/xforms/xforms-controls/page-flow.xpl"/>

    <!-- Standalone XForms To Do Lists example -->
    <page path-info="/xforms-todo*" model="/examples/xforms/xforms-todo/page-flow.xpl"/>

    <!-- Standalone XForms Upload example -->
    <page path-info="/xforms-upload*" model="/examples/xforms/xforms-upload/page-flow.xpl"/>

    <!-- Standalone XForms Sandbox example -->
    <page path-info="/xforms-sandbox*" model="/examples/sandbox/xforms/page-flow.xpl"/>

    <!-- Standalone XForms Dynamic Image example -->
    <page path-info="/xforms-dynamic-image*" model="/examples/xforms/xforms-dynamic-image/page-flow.xpl"/>

    <!-- Standalone XForms i18n example -->
    <page path-info="/xforms-i18n*" model="/examples/xforms/xforms-i18n/page-flow.xpl"/>

    <!-- Standalone PDF Upload example (contribution) -->
    <page path-info="/pdf-upload*" model="/examples/pdf/pdf-upload/page-flow.xpl"/>

    <!-- Java profiler  -->
    <page path-info="/profiler/*" model="/examples/profiler/page-flow.xpl"/>

    <!-- Documentation -->
    <!--<page path-info="/examples/doc" view="/doc/stub-view.xml"/>-->
    <!--<page path-info="/doc/book" model="/doc/book/model.xpl"/>-->
    <page path-info="/doc/" matcher="oxf:perl5-matcher"
        default-submission="/doc/default-submission.xml" model="/doc/doc-model.xpl" view="/doc/doc-view.xpl">
        <setvalue ref="/form/pdf" parameter="pdf"/>
    </page>
    <page path-info="/doc/(.*)" matcher="oxf:perl5-matcher"
            default-submission="/doc/default-submission.xml" model="/doc/doc-model.xpl" view="/doc/doc-view.xpl">
        <setvalue ref="/form/page" matcher-group="1"/>
        <setvalue ref="/form/pdf" parameter="pdf"/>
    </page>

    <!-- Portal -->
    <page path-info="/examples/portal/*" model="/portal/config/model.xpl"/>

    <!-- OXFMark -->
    <page path-info="/examples/oxfmark-machines" model="/oxfmark/machines.xpl"/>
    <page path-info="/examples/oxfmark-vms" model="/oxfmark/vms.xpl"/>

    <!-- XTech Article -->
    <page path-info="/xtech*" model="/doc/xtech-2005/model.xpl" view="/doc/xtech-2005/docbook/html/docbook.xsl"/>

    <!-- XPL specification -->
    <page path-info="/2005/SUBM-xpl-20050222/" model="/doc/xpl-spec/model.xpl"/>
    <page path-info="/2005/xpl/" model="/doc/xpl-spec/model.xpl"/>

    <!-- "Not Found" page displayed when no page matches the request URL -->
    <page id="not-found" path-info="/not-found" view="/config/not-found.xml"/>

    <epilogue url="/config/epilogue.xpl"/>
    <not-found-handler page="not-found"/>

</config>